{"type": "Feature", "geometry": {"type": "Point", "coordinates": [-0.141928, 51.525836]}, "properties": {"documentation-url": "https://historicengland.org.uk/listing/the-list/list-entry/1444842", "end-date": "2022-05-02", "start-date": "2017-05-03", "point": "POINT (-0.141928 51.525836)", "name": "Roman Catholic Church of St Anne", "organisation": "government-organisation:PB1164", "geography": "certificate-of-immunity:1444842", "slug": "/certificate-of-immunity/certificate-of-immunity/1444842", "entity": 57118, "entry-date": "2021-09-09"}}