{"type": "Feature", "geometry": {"type": "Point", "coordinates": [-4.169099, 50.365548]}, "properties": {"start-date": "2020-01-16", "organisation": "government-organisation:PB1164", "geography": "certificate-of-immunity:1467137", "name": "Fomer Maritime Headquarters, Mount Wise", "end-date": "2025-01-15", "documentation-url": "https://historicengland.org.uk/listing/the-list/list-entry/1467137", "point": "POINT (-4.169099 50.365548)", "slug": "/certificate-of-immunity/certificate-of-immunity/1467137", "entity": 57254, "entry-date": "2021-09-09"}}