{"type": "Feature", "geometry": {"type": "Point", "coordinates": [-4.169099, 50.365548]}, "properties": {"end-date": "2025-01-15", "start-date": "2020-01-16", "point": "POINT (-4.169099 50.365548)", "name": "Fomer Maritime Headquarters, Mount Wise", "documentation-url": "https://historicengland.org.uk/listing/the-list/list-entry/1467137", "geography": "certificate-of-immunity:1467137", "slug": "/certificate-of-immunity/certificate-of-immunity/1467137", "entry-date": "2021-06-01"}}