{"type": "Feature", "geometry": {"type": "Point", "coordinates": [-0.775282, 50.831121]}, "properties": {"name": "Air Raid Shelters at Chichester High School", "documentation-url": "https://historicengland.org.uk/listing/the-list/list-entry/1471622", "end-date": "2026-04-27", "geography": "certificate-of-immunity:1471622", "start-date": "2021-04-28", "point": "POINT (-0.775282 50.831121)", "slug": "/certificate-of-immunity/certificate-of-immunity/1471622", "entry-date": "2021-06-30"}}