{"type": "Feature", "geometry": {"type": "Point", "coordinates": [-0.775282, 50.831121]}, "properties": {"organisation": "government-organisation:PB1164", "geography": "certificate-of-immunity:1471622", "name": "Air Raid Shelters at Chichester High School", "documentation-url": "https://historicengland.org.uk/listing/the-list/list-entry/1471622", "point": "POINT (-0.775282 50.831121)", "start-date": "2021-04-28", "end-date": "2026-04-27", "slug": "/certificate-of-immunity/certificate-of-immunity/1471622", "entity": 57281, "entry-date": "2021-09-09"}}