{"type": "Feature", "geometry": {"type": "Point", "coordinates": [-0.099019, 51.494543]}, "properties": {"end-date": "2023-10-22", "documentation-url": "https://historicengland.org.uk/listing/the-list/list-entry/1460003", "start-date": "2018-10-23", "name": "The Coronet", "point": "POINT (-0.099019 51.494543)", "geography": "certificate-of-immunity:1460003", "slug": "/certificate-of-immunity/certificate-of-immunity/1460003", "entry-date": "2021-06-01"}}