{"type": "Feature", "geometry": {"type": "Point", "coordinates": [-0.099019, 51.494543]}, "properties": {"point": "POINT (-0.099019 51.494543)", "geography": "certificate-of-immunity:1460003", "organisation": "government-organisation:PB1164", "end-date": "2023-10-22", "name": "The Coronet", "documentation-url": "https://historicengland.org.uk/listing/the-list/list-entry/1460003", "start-date": "2018-10-23", "slug": "/certificate-of-immunity/certificate-of-immunity/1460003", "entity": 57211, "entry-date": "2021-10-01"}}