{"type": "Feature", "geometry": {"type": "Point", "coordinates": [-0.866117, 50.806645]}, "properties": {"end-date": "2022-09-28", "geography": "certificate-of-immunity:1448394", "name": "Old Haven", "start-date": "2017-09-29", "documentation-url": "https://historicengland.org.uk/listing/the-list/list-entry/1448394", "point": "POINT (-0.866117 50.806645)", "slug": "/certificate-of-immunity/certificate-of-immunity/1448394", "entry-date": "2021-08-13"}}