{"type": "Feature", "geometry": {"type": "Point", "coordinates": [-0.866117, 50.806645]}, "properties": {"start-date": "2017-09-29", "end-date": "2022-09-28", "organisation": "government-organisation:PB1164", "documentation-url": "https://historicengland.org.uk/listing/the-list/list-entry/1448394", "point": "POINT (-0.866117 50.806645)", "geography": "certificate-of-immunity:1448394", "name": "Old Haven", "slug": "/certificate-of-immunity/certificate-of-immunity/1448394", "entity": 57138, "entry-date": "2021-11-01"}}