{"type": "Feature", "geometry": {"type": "Point", "coordinates": [-0.116431, 51.511947]}, "properties": {"start-date": "2019-11-14", "geography": "certificate-of-immunity:1466829", "point": "POINT (-0.116431 51.511947)", "name": "Strand Building", "end-date": "2024-11-13", "documentation-url": "https://historicengland.org.uk/listing/the-list/list-entry/1466829", "slug": "/certificate-of-immunity/certificate-of-immunity/1466829", "entry-date": "2021-08-01"}}