{"type": "Feature", "geometry": {"type": "Point", "coordinates": [-0.116431, 51.511947]}, "properties": {"documentation-url": "https://historicengland.org.uk/listing/the-list/list-entry/1466829", "name": "Strand Building", "end-date": "2024-11-13", "geography": "certificate-of-immunity:1466829", "point": "POINT (-0.116431 51.511947)", "start-date": "2019-11-14", "slug": "/certificate-of-immunity/certificate-of-immunity/1466829", "entry-date": "2021-06-30"}}