{"type": "Feature", "geometry": {"type": "Point", "coordinates": [-1.13819, 51.515396]}, "properties": {"point": "POINT (-1.138190 51.515396)", "documentation-url": "https://historicengland.org.uk/listing/the-list/list-entry/1468491", "geography": "certificate-of-immunity:1468491", "name": "Jordleys", "end-date": "2025-02-26", "start-date": "2020-02-27", "slug": "/certificate-of-immunity/certificate-of-immunity/1468491", "entry-date": "2021-08-31", "organisation": "government-organisation:PB1164"}}