{"type": "Feature", "geometry": {"type": "Point", "coordinates": [-1.13819, 51.515396]}, "properties": {"name": "Jordleys", "end-date": "2025-02-26", "point": "POINT (-1.138190 51.515396)", "geography": "certificate-of-immunity:1468491", "start-date": "2020-02-27", "documentation-url": "https://historicengland.org.uk/listing/the-list/list-entry/1468491", "slug": "/certificate-of-immunity/certificate-of-immunity/1468491", "entry-date": "2021-06-30"}}