{"type": "Feature", "geometry": {"type": "Point", "coordinates": [-1.13819, 51.515396]}, "properties": {"documentation-url": "https://historicengland.org.uk/listing/the-list/list-entry/1468491", "name": "Jordleys", "point": "POINT (-1.138190 51.515396)", "start-date": "2020-02-27", "geography": "certificate-of-immunity:1468491", "organisation": "government-organisation:PB1164", "end-date": "2025-02-26", "slug": "/certificate-of-immunity/certificate-of-immunity/1468491", "entity": 57259, "entry-date": "2021-10-01"}}