{"type": "Feature", "geometry": {"type": "Point", "coordinates": [-4.187057, 50.384636]}, "properties": {"organisation": "government-organisation:PB1164", "geography": "certificate-of-immunity:1470271", "start-date": "2020-07-23", "end-date": "2025-07-22", "name": "Buildings N125, N093 and N125a, Devonport Dockyard", "point": "POINT (-4.187057 50.384636)", "documentation-url": "https://historicengland.org.uk/listing/the-list/list-entry/1470271", "slug": "/certificate-of-immunity/certificate-of-immunity/1470271", "entity": 57269, "entry-date": "2021-10-01"}}