{"type": "Feature", "geometry": {"type": "Point", "coordinates": [-4.187057, 50.384636]}, "properties": {"documentation-url": "https://historicengland.org.uk/listing/the-list/list-entry/1470271", "point": "POINT (-4.187057 50.384636)", "geography": "certificate-of-immunity:1470271", "name": "Buildings N125, N093 and N125a, Devonport Dockyard", "end-date": "2025-07-22", "start-date": "2020-07-23", "slug": "/certificate-of-immunity/certificate-of-immunity/1470271", "entry-date": "2021-08-31", "organisation": "government-organisation:PB1164"}}