{"type": "Feature", "geometry": {"type": "Point", "coordinates": [-4.187057, 50.384636]}, "properties": {"geography": "certificate-of-immunity:1470271", "documentation-url": "https://historicengland.org.uk/listing/the-list/list-entry/1470271", "start-date": "2020-07-23", "end-date": "2025-07-22", "point": "POINT (-4.187057 50.384636)", "name": "Buildings N125, N093 and N125a, Devonport Dockyard", "slug": "/certificate-of-immunity/certificate-of-immunity/1470271", "entry-date": "2021-06-01"}}