{"type": "Feature", "geometry": {"type": "Point", "coordinates": [1.079085, 51.274492]}, "properties": {"geography": "certificate-of-immunity:1466481", "documentation-url": "https://historicengland.org.uk/listing/the-list/list-entry/1466481", "name": "Former St Mary Bredin School", "organisation": "government-organisation:PB1164", "point": "POINT (1.079085 51.274492)", "start-date": "2020-05-28", "end-date": "2025-05-27", "slug": "/certificate-of-immunity/certificate-of-immunity/1466481", "entity": 57247, "entry-date": "2021-09-09"}}