{"type": "Feature", "geometry": {"type": "Point", "coordinates": [1.079085, 51.274492]}, "properties": {"point": "POINT (1.079085 51.274492)", "organisation": "government-organisation:PB1164", "name": "Former St Mary Bredin School", "start-date": "2020-05-28", "end-date": "2025-05-27", "documentation-url": "https://historicengland.org.uk/listing/the-list/list-entry/1466481", "geography": "certificate-of-immunity:1466481", "slug": "/certificate-of-immunity/certificate-of-immunity/1466481", "entity": 57247, "entry-date": "2021-11-01"}}