{"type": "Feature", "geometry": {"type": "Point", "coordinates": [1.079085, 51.274492]}, "properties": {"name": "Former St Mary Bredin School", "point": "POINT (1.079085 51.274492)", "documentation-url": "https://historicengland.org.uk/listing/the-list/list-entry/1466481", "start-date": "2020-05-28", "geography": "certificate-of-immunity:1466481", "end-date": "2025-05-27", "slug": "/certificate-of-immunity/certificate-of-immunity/1466481", "entry-date": "2021-08-01"}}