{"type": "Feature", "geometry": {"type": "Point", "coordinates": [-0.146707, 51.516852]}, "properties": {"documentation-url": "https://historicengland.org.uk/listing/the-list/list-entry/1457042", "end-date": "2023-07-04", "name": "8-10 Wigmore Street", "start-date": "2018-07-05", "point": "POINT (-0.146707 51.516852)", "geography": "certificate-of-immunity:1457042", "slug": "/certificate-of-immunity/certificate-of-immunity/1457042", "entry-date": "2021-06-30"}}