{"type": "Feature", "geometry": {"type": "Point", "coordinates": [-0.146707, 51.516852]}, "properties": {"end-date": "2023-07-04", "documentation-url": "https://historicengland.org.uk/listing/the-list/list-entry/1457042", "start-date": "2018-07-05", "organisation": "government-organisation:PB1164", "point": "POINT (-0.146707 51.516852)", "geography": "certificate-of-immunity:1457042", "name": "8-10 Wigmore Street", "slug": "/certificate-of-immunity/certificate-of-immunity/1457042", "entity": 57200, "entry-date": "2021-10-15"}}