{"type": "Feature", "geometry": {"type": "Point", "coordinates": [-0.096217, 51.517864]}, "properties": {"start-date": "2019-08-21", "geography": "certificate-of-immunity:1465513", "documentation-url": "https://historicengland.org.uk/listing/the-list/list-entry/1465513", "name": "Museum of London and Bastion House", "end-date": "2024-08-20", "point": "POINT (-0.096217 51.517864)", "slug": "/certificate-of-immunity/certificate-of-immunity/1465513", "entry-date": "2021-08-13"}}