{"type": "Feature", "geometry": {"type": "Point", "coordinates": [-0.096217, 51.517864]}, "properties": {"documentation-url": "https://historicengland.org.uk/listing/the-list/list-entry/1465513", "start-date": "2019-08-21", "end-date": "2024-08-20", "organisation": "government-organisation:PB1164", "name": "Museum of London and Bastion House", "point": "POINT (-0.096217 51.517864)", "geography": "certificate-of-immunity:1465513", "slug": "/certificate-of-immunity/certificate-of-immunity/1465513", "entity": 57244, "entry-date": "2021-09-09"}}