{"type": "Feature", "geometry": {"type": "Point", "coordinates": [-0.096217, 51.517864]}, "properties": {"geography": "certificate-of-immunity:1465513", "name": "Museum of London and Bastion House", "point": "POINT (-0.096217 51.517864)", "end-date": "2024-08-20", "start-date": "2019-08-21", "documentation-url": "https://historicengland.org.uk/listing/the-list/list-entry/1465513", "slug": "/certificate-of-immunity/certificate-of-immunity/1465513", "entry-date": "2021-06-01"}}