{"type": "Feature", "geometry": {"type": "Point", "coordinates": [-1.743074, 52.518576]}, "properties": {"point": "POINT (-1.743074 52.518576)", "organisation": "government-organisation:PB1164", "geography": "certificate-of-immunity:1477543", "name": "Water Orton Railway Station", "end-date": "2026-08-31", "start-date": "2021-09-01", "documentation-url": "https://historicengland.org.uk/listing/the-list/list-entry/1477543", "slug": "/certificate-of-immunity/certificate-of-immunity/1477543", "entity": 506029, "entry-date": "2021-10-15"}}