{"type": "Feature", "geometry": {"type": "Point", "coordinates": [-1.743074, 52.518576]}, "properties": {"documentation-url": "https://historicengland.org.uk/listing/the-list/list-entry/1477543", "start-date": "2021-09-01", "name": "Water Orton Railway Station", "organisation": "government-organisation:PB1164", "geography": "certificate-of-immunity:1477543", "point": "POINT (-1.743074 52.518576)", "end-date": "2026-08-31", "slug": "/certificate-of-immunity/certificate-of-immunity/1477543", "entity": null, "entry-date": "2021-09-09"}}