{"type": "Feature", "geometry": {"type": "Point", "coordinates": [0.041044, 51.494372]}, "properties": {"geography": "certificate-of-immunity:1452599", "name": "18-32 Bowater Road", "end-date": "2023-10-02", "start-date": "2018-10-03", "documentation-url": "https://historicengland.org.uk/listing/the-list/list-entry/1452599", "point": "POINT (0.041044 51.494372)", "slug": "/certificate-of-immunity/certificate-of-immunity/1452599", "entry-date": "2021-08-13"}}