{"type": "Feature", "geometry": {"type": "Point", "coordinates": [0.041044, 51.494372]}, "properties": {"name": "18-32 Bowater Road", "geography": "certificate-of-immunity:1452599", "documentation-url": "https://historicengland.org.uk/listing/the-list/list-entry/1452599", "point": "POINT (0.041044 51.494372)", "start-date": "2018-10-03", "end-date": "2023-10-02", "slug": "/certificate-of-immunity/certificate-of-immunity/1452599", "entry-date": "2021-05-28"}}