{"type": "Feature", "geometry": {"type": "Point", "coordinates": [0.041044, 51.494372]}, "properties": {"organisation": "government-organisation:PB1164", "name": "18-32 Bowater Road", "start-date": "2018-10-03", "point": "POINT (0.041044 51.494372)", "geography": "certificate-of-immunity:1452599", "end-date": "2023-10-02", "documentation-url": "https://historicengland.org.uk/listing/the-list/list-entry/1452599", "slug": "/certificate-of-immunity/certificate-of-immunity/1452599", "entity": 57156, "entry-date": "2021-11-01"}}