{"type": "Feature", "geometry": {"type": "Point", "coordinates": [-3.466894, 50.576785]}, "properties": {"start-date": "2018-05-15", "documentation-url": "https://historicengland.org.uk/listing/the-list/list-entry/1454753", "geography": "certificate-of-immunity:1454753", "point": "POINT (-3.466894 50.576785)", "end-date": "2023-05-14", "name": "Boat Cove Breakwater", "slug": "/certificate-of-immunity/certificate-of-immunity/1454753", "entry-date": "2021-06-01"}}