{"type": "Feature", "geometry": {"type": "Point", "coordinates": [-3.466894, 50.576785]}, "properties": {"point": "POINT (-3.466894 50.576785)", "end-date": "2023-05-14", "organisation": "government-organisation:PB1164", "start-date": "2018-05-15", "documentation-url": "https://historicengland.org.uk/listing/the-list/list-entry/1454753", "geography": "certificate-of-immunity:1454753", "name": "Boat Cove Breakwater", "slug": "/certificate-of-immunity/certificate-of-immunity/1454753", "entity": 57181, "entry-date": "2021-09-09"}}