{"type": "Feature", "geometry": {"type": "Point", "coordinates": [0.042233, 51.494032]}, "properties": {"geography": "certificate-of-immunity:1469332", "point": "POINT (0.042233 51.494032)", "organisation": "government-organisation:PB1164", "end-date": "2025-05-26", "start-date": "2020-05-27", "documentation-url": "https://historicengland.org.uk/listing/the-list/list-entry/1469332", "name": "17-21 Bowater Road", "slug": "/certificate-of-immunity/certificate-of-immunity/1469332", "entity": 57265, "entry-date": "2021-09-09"}}