{"type": "Feature", "geometry": {"type": "Point", "coordinates": [0.042233, 51.494032]}, "properties": {"end-date": "2025-05-26", "name": "17-21 Bowater Road", "geography": "certificate-of-immunity:1469332", "documentation-url": "https://historicengland.org.uk/listing/the-list/list-entry/1469332", "point": "POINT (0.042233 51.494032)", "start-date": "2020-05-27", "slug": "/certificate-of-immunity/certificate-of-immunity/1469332", "entry-date": "2021-06-30"}}