{"type": "Feature", "geometry": {"type": "Point", "coordinates": [-0.036605, 51.431032]}, "properties": {"end-date": "2023-01-08", "geography": "certificate-of-immunity:1452259", "name": "Gasholder No 7, Bell Green", "organisation": "government-organisation:PB1164", "documentation-url": "https://historicengland.org.uk/listing/the-list/list-entry/1452259", "point": "POINT (-0.036605 51.431032)", "start-date": "2018-01-09", "slug": "/certificate-of-immunity/certificate-of-immunity/1452259", "entity": 57152, "entry-date": "2021-09-09"}}