{"type": "Feature", "geometry": {"type": "Point", "coordinates": [-0.036605, 51.431032]}, "properties": {"point": "POINT (-0.036605 51.431032)", "start-date": "2018-01-09", "documentation-url": "https://historicengland.org.uk/listing/the-list/list-entry/1452259", "geography": "certificate-of-immunity:1452259", "end-date": "2023-01-08", "name": "Gasholder No 7, Bell Green", "slug": "/certificate-of-immunity/certificate-of-immunity/1452259", "entry-date": "2021-06-01"}}