{"type": "Feature", "geometry": {"type": "Point", "coordinates": [-1.260934, 51.624039]}, "properties": {"point": "POINT (-1.260934 51.624039)", "end-date": "2023-03-21", "name": "Didcot A Power Station", "start-date": "2018-03-22", "geography": "certificate-of-immunity:1454387", "documentation-url": "https://historicengland.org.uk/listing/the-list/list-entry/1454387", "slug": "/certificate-of-immunity/certificate-of-immunity/1454387", "entry-date": "2021-08-01"}}