{"type": "Feature", "geometry": {"type": "Point", "coordinates": [-1.260934, 51.624039]}, "properties": {"point": "POINT (-1.260934 51.624039)", "geography": "certificate-of-immunity:1454387", "name": "Didcot A Power Station", "end-date": "2023-03-21", "documentation-url": "https://historicengland.org.uk/listing/the-list/list-entry/1454387", "organisation": "government-organisation:PB1164", "start-date": "2018-03-22", "slug": "/certificate-of-immunity/certificate-of-immunity/1454387", "entity": 57170, "entry-date": "2021-09-09"}}