{"type": "Feature", "geometry": {"type": "Point", "coordinates": [-1.92437, 52.470927]}, "properties": {"name": "Birmingham Chamber of Commerce", "start-date": "2021-08-24", "geography": "certificate-of-immunity:1475208", "point": "POINT (-1.924370 52.470927)", "documentation-url": "https://historicengland.org.uk/listing/the-list/list-entry/1475208", "end-date": "2026-08-23", "organisation": "government-organisation:PB1164", "slug": "/certificate-of-immunity/certificate-of-immunity/1475208", "entity": null, "entry-date": "2021-09-09"}}