{"type": "Feature", "geometry": {"type": "Point", "coordinates": [-1.39087, 50.908238]}, "properties": {"end-date": "2023-07-16", "geography": "certificate-of-immunity:1457264", "start-date": "2018-07-17", "point": "POINT (-1.390870 50.908238)", "organisation": "government-organisation:PB1164", "documentation-url": "https://historicengland.org.uk/listing/the-list/list-entry/1457264", "name": "Gasholder Number 9, former Southampton Gasworks", "slug": "/certificate-of-immunity/certificate-of-immunity/1457264", "entity": 57202, "entry-date": "2021-10-15"}}