{"type": "Feature", "geometry": {"type": "Point", "coordinates": [-1.39087, 50.908238]}, "properties": {"name": "Gasholder Number 9, former Southampton Gasworks", "start-date": "2018-07-17", "end-date": "2023-07-16", "geography": "certificate-of-immunity:1457264", "documentation-url": "https://historicengland.org.uk/listing/the-list/list-entry/1457264", "point": "POINT (-1.390870 50.908238)", "slug": "/certificate-of-immunity/certificate-of-immunity/1457264", "entry-date": "2021-08-01"}}