{"type": "Feature", "geometry": {"type": "Point", "coordinates": [-0.144744, 51.508645]}, "properties": {"start-date": "2019-06-10", "name": "Lansdowne House, Berkeley Square", "documentation-url": "https://historicengland.org.uk/listing/the-list/list-entry/1463486", "geography": "certificate-of-immunity:1463486", "end-date": "2024-06-09", "point": "POINT (-0.144744 51.508645)", "slug": "/certificate-of-immunity/certificate-of-immunity/1463486", "entry-date": "2021-06-30"}}