{"type": "Feature", "geometry": {"type": "Point", "coordinates": [-0.144744, 51.508645]}, "properties": {"organisation": "government-organisation:PB1164", "end-date": "2024-06-09", "start-date": "2019-06-10", "name": "Lansdowne House, Berkeley Square", "geography": "certificate-of-immunity:1463486", "point": "POINT (-0.144744 51.508645)", "documentation-url": "https://historicengland.org.uk/listing/the-list/list-entry/1463486", "slug": "/certificate-of-immunity/certificate-of-immunity/1463486", "entity": 57224, "entry-date": "2021-09-09"}}