{"type": "Feature", "geometry": {"type": "Point", "coordinates": [-3.486089, 50.55298]}, "properties": {"end-date": "2023-04-09", "name": "Former platelayer's cabin 200m south of Sprey Point", "documentation-url": "https://historicengland.org.uk/listing/the-list/list-entry/1454881", "geography": "certificate-of-immunity:1454881", "organisation": "government-organisation:PB1164", "start-date": "2018-04-10", "point": "POINT (-3.486089 50.552980)", "slug": "/certificate-of-immunity/certificate-of-immunity/1454881", "entity": 57183, "entry-date": "2021-09-09"}}