{"type": "Feature", "geometry": {"type": "Point", "coordinates": [-3.486089, 50.55298]}, "properties": {"end-date": "2023-04-09", "point": "POINT (-3.486089 50.552980)", "geography": "certificate-of-immunity:1454881", "start-date": "2018-04-10", "documentation-url": "https://historicengland.org.uk/listing/the-list/list-entry/1454881", "name": "Former platelayer's cabin 200m south of Sprey Point", "slug": "/certificate-of-immunity/certificate-of-immunity/1454881", "entry-date": "2021-06-30"}}