{"type": "Feature", "geometry": {"type": "Point", "coordinates": [-0.106765, 51.51406]}, "properties": {"name": "Chronicle House, 72-78 Fleet Street", "start-date": "2020-07-24", "geography": "certificate-of-immunity:1470697", "end-date": "2025-07-23", "documentation-url": "https://historicengland.org.uk/listing/the-list/list-entry/1470697", "point": "POINT (-0.106765 51.514060)", "organisation": "government-organisation:PB1164", "slug": "/certificate-of-immunity/certificate-of-immunity/1470697", "entity": 57274, "entry-date": "2021-10-15"}}