{"type": "Feature", "geometry": {"type": "Point", "coordinates": [-1.627989, 53.693032]}, "properties": {"documentation-url": "https://historicengland.org.uk/listing/the-list/list-entry/1464998", "end-date": "2025-10-08", "name": "Dewsbury Market Hall", "organisation": "government-organisation:PB1164", "start-date": "2020-10-09", "point": "POINT (-1.627989 53.693032)", "geography": "certificate-of-immunity:1464998", "slug": "/certificate-of-immunity/certificate-of-immunity/1464998", "entity": 57242, "entry-date": "2021-09-09"}}