{"type": "Feature", "geometry": {"type": "Point", "coordinates": [-1.627989, 53.693032]}, "properties": {"point": "POINT (-1.627989 53.693032)", "start-date": "2020-10-09", "name": "Dewsbury Market Hall", "documentation-url": "https://historicengland.org.uk/listing/the-list/list-entry/1464998", "end-date": "2025-10-08", "geography": "certificate-of-immunity:1464998", "slug": "/certificate-of-immunity/certificate-of-immunity/1464998", "entry-date": "2021-06-01"}}