{"type": "Feature", "geometry": {"type": "Point", "coordinates": [-0.12009, 51.519102]}, "properties": {"geography": "certificate-of-immunity:1463729", "point": "POINT (-0.120090 51.519102)", "documentation-url": "https://historicengland.org.uk/listing/the-list/list-entry/1463729", "end-date": "2024-07-14", "name": "Cochrane Theatre and attached Administrative Block", "start-date": "2019-07-15", "slug": "/certificate-of-immunity/certificate-of-immunity/1463729", "entry-date": "2021-08-01"}}