{"type": "Feature", "geometry": {"type": "Point", "coordinates": [-0.12009, 51.519102]}, "properties": {"point": "POINT (-0.120090 51.519102)", "start-date": "2019-07-15", "organisation": "government-organisation:PB1164", "end-date": "2024-07-14", "documentation-url": "https://historicengland.org.uk/listing/the-list/list-entry/1463729", "name": "Cochrane Theatre and attached Administrative Block", "geography": "certificate-of-immunity:1463729", "slug": "/certificate-of-immunity/certificate-of-immunity/1463729", "entity": 57232, "entry-date": "2021-11-01"}}