{"type": "Feature", "geometry": {"type": "Point", "coordinates": [-3.464403, 50.579483]}, "properties": {"geography": "certificate-of-immunity:1454747", "end-date": "2023-05-14", "name": "Colonnade Breakwater and attached basin walls", "start-date": "2018-05-15", "documentation-url": "https://historicengland.org.uk/listing/the-list/list-entry/1454747", "organisation": "government-organisation:PB1164", "point": "POINT (-3.464403 50.579483)", "slug": "/certificate-of-immunity/certificate-of-immunity/1454747", "entity": 57177, "entry-date": "2021-09-09"}}