{"type": "Feature", "geometry": {"type": "Point", "coordinates": [-3.464403, 50.579483]}, "properties": {"start-date": "2018-05-15", "documentation-url": "https://historicengland.org.uk/listing/the-list/list-entry/1454747", "geography": "certificate-of-immunity:1454747", "name": "Colonnade Breakwater and attached basin walls", "end-date": "2023-05-14", "point": "POINT (-3.464403 50.579483)", "slug": "/certificate-of-immunity/certificate-of-immunity/1454747", "entry-date": "2021-06-30"}}