{"type": "Feature", "geometry": {"type": "Point", "coordinates": [-2.743367, 54.333556]}, "properties": {"end-date": "2022-06-06", "point": "POINT (-2.743367 54.333556)", "start-date": "2017-06-07", "name": "Kendal Footbridge", "documentation-url": "https://historicengland.org.uk/listing/the-list/list-entry/1445950", "geography": "certificate-of-immunity:1445950", "slug": "/certificate-of-immunity/certificate-of-immunity/1445950", "entry-date": "2021-06-30"}}