{"type": "Feature", "geometry": {"type": "Point", "coordinates": [-2.743367, 54.333556]}, "properties": {"start-date": "2017-06-07", "geography": "certificate-of-immunity:1445950", "end-date": "2022-06-06", "organisation": "government-organisation:PB1164", "point": "POINT (-2.743367 54.333556)", "documentation-url": "https://historicengland.org.uk/listing/the-list/list-entry/1445950", "name": "Kendal Footbridge", "slug": "/certificate-of-immunity/certificate-of-immunity/1445950", "entity": 57127, "entry-date": "2021-09-09"}}