{"type": "Feature", "geometry": {"type": "Point", "coordinates": [-0.148269, 51.513437]}, "properties": {"point": "POINT (-0.148269 51.513437)", "end-date": "2021-08-29", "name": "Army Reserve Centre, 56 Davies Street, Westminster", "documentation-url": "https://historicengland.org.uk/listing/the-list/list-entry/1437275", "start-date": "2016-08-30", "geography": "certificate-of-immunity:1437275", "slug": "/certificate-of-immunity/certificate-of-immunity/1437275", "entry-date": "2021-08-13"}}