{"type": "Feature", "geometry": {"type": "Point", "coordinates": [-0.148269, 51.513437]}, "properties": {"documentation-url": "https://historicengland.org.uk/listing/the-list/list-entry/1437275", "point": "POINT (-0.148269 51.513437)", "start-date": "2016-08-30", "geography": "certificate-of-immunity:1437275", "name": "Army Reserve Centre, 56 Davies Street, Westminster", "end-date": "2021-08-29", "slug": "/certificate-of-immunity/certificate-of-immunity/1437275", "entry-date": "2021-08-31", "organisation": "government-organisation:PB1164"}}