{"type": "Feature", "geometry": {"type": "Point", "coordinates": [-2.759629, 54.345332]}, "properties": {"geography": "certificate-of-immunity:1445943", "organisation": "government-organisation:PB1164", "name": "High Sparrow Mire", "end-date": "2022-06-06", "documentation-url": "https://historicengland.org.uk/listing/the-list/list-entry/1445943", "point": "POINT (-2.759629 54.345332)", "start-date": "2017-06-07", "slug": "/certificate-of-immunity/certificate-of-immunity/1445943", "entity": 57124, "entry-date": "2021-11-01"}}