{"type": "Feature", "geometry": {"type": "Point", "coordinates": [-2.759629, 54.345332]}, "properties": {"name": "High Sparrow Mire", "geography": "certificate-of-immunity:1445943", "point": "POINT (-2.759629 54.345332)", "documentation-url": "https://historicengland.org.uk/listing/the-list/list-entry/1445943", "start-date": "2017-06-07", "end-date": "2022-06-06", "slug": "/certificate-of-immunity/certificate-of-immunity/1445943", "entry-date": "2021-06-30"}}